{
  "success": true,
  "data": [
    {
      "price": 1742.9,
      "timestamp": "2024-11-20T16:46:32.016060",
      "available_amount": "456.8747 USDT\n17,000.00 ~ 18,000.00 NGN",
      "payment_methods": "Bank Transfer",
      "merchant_name": "Buy USDT"
    },
    {
      "price": 1742.99,
      "timestamp": "2024-11-20T16:46:32.071451",
      "available_amount": "88.5254 USDT\n15,000.00 ~ 20,000.00 NGN",
      "payment_methods": "Bank Transfer",
      "merchant_name": "Buy USDT"
    },
    {
      "price": 1743.0,
      "timestamp": "2024-11-20T16:46:32.124689",
      "available_amount": "180.6382 USDT\n5,500.00 ~ 25,000.00 NGN",
      "payment_methods": "Opay",
      "merchant_name": "Buy USDT"
    },
    {
      "price": 1743.0,
      "timestamp": "2024-11-20T16:46:32.181182",
      "available_amount": "297.0000 USDT\n517,671.00 ~ 517,671.00 NGN",
      "payment_methods": "Bank Transfer",
      "merchant_name": "Buy USDT"
    },
    {
      "price": 1745.0,
      "timestamp": "2024-11-20T16:46:31.952426",
      "available_amount": "60.0000 USDT\n20,000.00 ~ 90,000.00 NGN",
      "payment_methods": "Bank Transfer",
      "merchant_name": "Buy USDT"
    }
  ],
  "metadata": {
    "token": "USDT",
    "fiat": "NGN",
    "action_type": "buy",
    "timestamp": "2024-11-20T16:46:32.319514",
    "total_rows_found": 11,
    "valid_listings_found": 5
  }
}