{
  "success": true,
  "data": [
    {
      "price": 1740.0,
      "timestamp": "2024-11-20T11:00:55.610025",
      "available_amount": "120.5969 USDT\n10,000.00 ~ 20,000.00 NGN",
      "payment_methods": "Bank Transfer",
      "merchant_name": "Buy USDT"
    },
    {
      "price": 1740.6,
      "timestamp": "2024-11-20T11:00:55.662854",
      "available_amount": "612.7403 USDT\n10,000.00 ~ 20,000.00 NGN",
      "payment_methods": "Bank Transfer",
      "merchant_name": "Buy USDT"
    },
    {
      "price": 1741.0,
      "timestamp": "2024-11-20T11:00:55.716453",
      "available_amount": "87.0246 USDT\n15,000.00 ~ 20,000.00 NGN",
      "payment_methods": "Bank Transfer",
      "merchant_name": "Buy USDT"
    },
    {
      "price": 1741.0,
      "timestamp": "2024-11-20T11:00:55.764567",
      "available_amount": "21.5621 USDT\n4,500.00 ~ 20,000.00 NGN",
      "payment_methods": "Bank Transfer",
      "merchant_name": "Buy USDT"
    },
    {
      "price": 1742.98,
      "timestamp": "2024-11-20T11:00:55.548456",
      "available_amount": "250.6727 USDT\n30,000.00 ~ 300,000.00 NGN",
      "payment_methods": "Bank Transfer",
      "merchant_name": "Buy USDT"
    }
  ],
  "metadata": {
    "token": "USDT",
    "fiat": "NGN",
    "action_type": "buy",
    "timestamp": "2024-11-20T11:00:55.900926",
    "total_rows_found": 11,
    "valid_listings_found": 5
  }
}