{
  "success": true,
  "timestamp": "2024-12-02T21:49:52.019178",
  "bybit": [
    {
      "price": 1722.99,
      "timestamp": "2024-12-02T21:49:51.134349",
      "available_amount": "22.8165 USDT\n5,000 ~ 7,000 NGN",
      "payment_methods": "Bank Transfer",
      "merchant_name": "Buy USDT"
    },
    {
      "price": 1723.0,
      "timestamp": "2024-12-02T21:49:51.188792",
      "available_amount": "65.7988 USDT\n4,500 ~ 9,900 NGN",
      "payment_methods": "Bank Transfer",
      "merchant_name": "Buy USDT"
    },
    {
      "price": 1723.0,
      "timestamp": "2024-12-02T21:49:51.249402",
      "available_amount": "6.3756 USDT\n5,000 ~ 9,000 NGN",
      "payment_methods": "Bank Transfer",
      "merchant_name": "Buy USDT"
    },
    {
      "price": 1723.5,
      "timestamp": "2024-12-02T21:49:51.296825",
      "available_amount": "123.5832 USDT\n4,500 ~ 5,000 NGN",
      "payment_methods": "Bank Transfer",
      "merchant_name": "Buy USDT"
    },
    {
      "price": 1723.99,
      "timestamp": "2024-12-02T21:49:51.350836",
      "available_amount": "80.3275 USDT\n5,000 ~ 9,000 NGN",
      "payment_methods": "Bank Transfer",
      "merchant_name": "Buy USDT"
    }
  ],
  "binance": [
    {
      "price": 0.953,
      "timestamp": "2024-12-02T21:49:52.019097",
      "available_amount": "340.00",
      "payment_methods": "SEPAinstant",
      "merchant_name": "exchang-smart"
    },
    {
      "price": 0.956,
      "timestamp": "2024-12-02T21:49:52.019115",
      "available_amount": "186634.62",
      "payment_methods": "SEPA, BANK, SEPAinstant",
      "merchant_name": "CoinClan - 大额交易"
    },
    {
      "price": 0.956,
      "timestamp": "2024-12-02T21:49:52.019119",
      "available_amount": "2023.85",
      "payment_methods": "SEPA",
      "merchant_name": "AbuGhazi-Bank"
    },
    {
      "price": 0.957,
      "timestamp": "2024-12-02T21:49:52.019123",
      "available_amount": "66921.32",
      "payment_methods": "SEPAinstant, SEPA, BANK",
      "merchant_name": "SmartOTC"
    },
    {
      "price": 0.958,
      "timestamp": "2024-12-02T21:49:52.019127",
      "available_amount": "11504.82",
      "payment_methods": "SEPA, ZEN, BANK",
      "merchant_name": "MakSton_P2P"
    },
    {
      "price": 0.96,
      "timestamp": "2024-12-02T21:49:52.019131",
      "available_amount": "1799.23",
      "payment_methods": "ZEN",
      "merchant_name": "DERYBOS"
    }
  ]
}