{
  "success": true,
  "timestamp": "2024-11-30T04:00:39.174725",
  "bybit": [
    {
      "price": 1720.0,
      "timestamp": "2024-11-30T04:00:38.481194",
      "available_amount": "154.4967 USDT\n5,000 ~ 265,734.32 NGN",
      "payment_methods": "Bank Transfer",
      "merchant_name": "Buy USDT"
    },
    {
      "price": 1720.98,
      "timestamp": "2024-11-30T04:00:38.538322",
      "available_amount": "489.2836 USDT\n50,000 ~ 842,047.28 NGN",
      "payment_methods": "Bank Transfer",
      "merchant_name": "Buy USDT"
    },
    {
      "price": 1721.0,
      "timestamp": "2024-11-30T04:00:38.593286",
      "available_amount": "174.1097 USDT\n50,000 ~ 80,000 NGN",
      "payment_methods": "Bank Transfer",
      "merchant_name": "Buy USDT"
    },
    {
      "price": 1721.3,
      "timestamp": "2024-11-30T04:00:38.643611",
      "available_amount": "537.8081 USDT\n900,000 ~ 910,000 NGN",
      "payment_methods": "Bank Transfer",
      "merchant_name": "Buy USDT"
    },
    {
      "price": 1721.5,
      "timestamp": "2024-11-30T04:00:38.701730",
      "available_amount": "141.9111 USDT\n50,000 ~ 100,000 NGN",
      "payment_methods": "Bank Transfer",
      "merchant_name": "Buy USDT"
    }
  ],
  "binance": [
    {
      "price": 0.949,
      "timestamp": "2024-11-30T04:00:39.174657",
      "available_amount": "4183.47",
      "payment_methods": "SEPA, BANK, SEPAinstant",
      "merchant_name": "CoinClan - 大额交易"
    },
    {
      "price": 0.95,
      "timestamp": "2024-11-30T04:00:39.174670",
      "available_amount": "87331.87",
      "payment_methods": "SEPAinstant, SEPA, BANK",
      "merchant_name": "SmartOTC"
    },
    {
      "price": 0.95,
      "timestamp": "2024-11-30T04:00:39.174673",
      "available_amount": "21428.87",
      "payment_methods": "BANK, SEPAinstant, SEPA",
      "merchant_name": "HanarsOTC"
    },
    {
      "price": 0.954,
      "timestamp": "2024-11-30T04:00:39.174678",
      "available_amount": "38675.65",
      "payment_methods": "SEPA, BANK, SEPAinstant",
      "merchant_name": "Crypto-Simple"
    },
    {
      "price": 0.954,
      "timestamp": "2024-11-30T04:00:39.174681",
      "available_amount": "34043.25",
      "payment_methods": "SEPAinstant, SEPA, BANK, ZEN",
      "merchant_name": "AlteWay"
    },
    {
      "price": 0.955,
      "timestamp": "2024-11-30T04:00:39.174685",
      "available_amount": "4130.00",
      "payment_methods": "ZEN",
      "merchant_name": "DERYBOS"
    }
  ]
}